django-bkendoz/__init__.py
django-bkendoz/admin.py
django-bkendoz/apps.py
django-bkendoz/core.py
django-bkendoz/forms.py
django-bkendoz/models.py
django-bkendoz/serializers.py
django-bkendoz/tests.py
django-bkendoz/views.py
django-bkendoz/migrations/0001_initial.py
django-bkendoz/migrations/__init__.py
django-bkendoz/templatetags/__init__.py
django-bkendoz/templatetags/templates.py
django_bkendoz/__init__.py
django_bkendoz/admin.py
django_bkendoz/apps.py
django_bkendoz/core.py
django_bkendoz/forms.py
django_bkendoz/models.py
django_bkendoz/serializers.py
django_bkendoz/tests.py
django_bkendoz/views.py
django_bkendoz/migrations/0001_initial.py
django_bkendoz/migrations/__init__.py
django_bkendoz/templates/__init__.py
django_bkendoz/templates/auth/__init__.py
django_bkendoz/templates/auth/user_detail.html
django_bkendoz/templates/django_bkendoz/__init__.py
django_bkendoz/templates/django_bkendoz/dashboard.html
django_bkendoz/templates/django_bkendoz/dashboard_tpl.html
django_bkendoz/templates/django_bkendoz/datatable_list.html
django_bkendoz/templates/django_bkendoz/delete.html
django_bkendoz/templates/django_bkendoz/detail.html
django_bkendoz/templates/django_bkendoz/footer.html
django_bkendoz/templates/django_bkendoz/form_view.html
django_bkendoz/templates/django_bkendoz/globalhistory_list.html
django_bkendoz/templates/django_bkendoz/history.html
django_bkendoz/templates/django_bkendoz/history_changes.html
django_bkendoz/templates/django_bkendoz/history_global.html
django_bkendoz/templates/django_bkendoz/history_row.html
django_bkendoz/templates/django_bkendoz/import_xls.html
django_bkendoz/templates/django_bkendoz/import_xls_preview.html
django_bkendoz/templates/django_bkendoz/layout.html
django_bkendoz/templates/django_bkendoz/list.html
django_bkendoz/templates/django_bkendoz/oldtable.html
django_bkendoz/templates/django_bkendoz/table.html
django_bkendoz/templates/django_bkendoz/templates/__init__.py
django_bkendoz-1.0.7.dist-info/LICENSE
django_bkendoz-1.0.7.dist-info/METADATA
django_bkendoz-1.0.7.dist-info/WHEEL
django_bkendoz-1.0.7.dist-info/top_level.txt
django_bkendoz-1.0.7.dist-info/RECORD
