Metadata-Version: 2.1
Name: django-bkendoz
Version: 1.0.7
Summary: generic views for managing data
Home-page: https://pypi.org/project/django-bkendoz/
Author: lokpr
Author-email: oziatek@gmail.com
License: : OSI Approved :: MIT License
Platform: UNKNOWN
Requires-Python: >=3.6
